Metadata-Version: 2.1
Name: pptxtpl
Version: 0.0.4
Summary: generate pptx file with jinja2 template
Home-page: https://github.com/kalavt/Pptxtpl
Author: kalavt
Author-email: unknow@unknow.com
License: UNKNOWN
Platform: UNKNOWN
License-File: LICENSE
